arel/__init__.py
arel/_app.py
arel/_models.py
arel/_notify.py
arel/_types.py
arel/_watch.py
arel/py.typed
arel/data/client.js
arel-0.4.0.dist-info/licenses/LICENSE
arel-0.4.0.dist-info/METADATA
arel-0.4.0.dist-info/WHEEL
arel-0.4.0.dist-info/top_level.txt
arel-0.4.0.dist-info/RECORD
